modelscope_studio/__init__.py
modelscope_studio/external.py
modelscope_studio/version.py
modelscope_studio/components/__init__.py
modelscope_studio/components/antd/__init__.py
modelscope_studio/components/antd/components.py
modelscope_studio/components/antd/affix/__init__.py
modelscope_studio/components/antd/affix/__init__.pyi
modelscope_studio/components/antd/affix/templates/component/Index-BHm9L0_c.js
modelscope_studio/components/antd/affix/templates/component/affix-G92hGbth.js
modelscope_studio/components/antd/affix/templates/component/index.js
modelscope_studio/components/antd/affix/templates/component/style.css
modelscope_studio/components/antd/alert/__init__.py
modelscope_studio/components/antd/alert/__init__.pyi
modelscope_studio/components/antd/alert/error_boundary/__init__.py
modelscope_studio/components/antd/alert/error_boundary/__init__.pyi
modelscope_studio/components/antd/alert/error_boundary/templates/component/Index-CLo1j2Fn.js
modelscope_studio/components/antd/alert/error_boundary/templates/component/alert.error-boundary-BQJ3gTrs.js
modelscope_studio/components/antd/alert/error_boundary/templates/component/index.js
modelscope_studio/components/antd/alert/error_boundary/templates/component/style.css
modelscope_studio/components/antd/alert/templates/component/Index-C-wPaxXr.js
modelscope_studio/components/antd/alert/templates/component/alert-CPtJTX1x.js
modelscope_studio/components/antd/alert/templates/component/index.js
modelscope_studio/components/antd/alert/templates/component/style.css
modelscope_studio/components/antd/anchor/__init__.py
modelscope_studio/components/antd/anchor/__init__.pyi
modelscope_studio/components/antd/anchor/item/__init__.py
modelscope_studio/components/antd/anchor/item/__init__.pyi
modelscope_studio/components/antd/anchor/item/templates/component/Index-D0Hxk7z2.js
modelscope_studio/components/antd/anchor/item/templates/component/anchor.item-C4T4daV7.js
modelscope_studio-1.5.2.dist-info/METADATA
modelscope_studio-1.5.2.dist-info/WHEEL
modelscope_studio-1.5.2.dist-info/licenses/LICENSE
modelscope_studio-1.5.2.dist-info/RECORD
